Metadata-Version: 2.1
Name: weasyprint
Version: 54.1
Summary: The Awesome Document Factory
Keywords: html,css,pdf,converter
Author-email: Simon Sapin <simon.sapin@exyr.org>
Maintainer-email: CourtBouillon <contact@courtbouillon.org>
Requires-Python: >=3.6
Classifier: Development Status :: 5 - Production/Stable
Classifier: Intended Audience :: Developers
Classifier: License :: OSI Approved :: BSD License
Classifier: Operating System :: OS Independent
Classifier: Programming Language :: Python
Classifier: Programming Language :: Python :: 3
Classifier: Programming Language :: Python :: 3 :: Only
Classifier: Programming Language :: Python :: 3.6
Classifier: Programming Language :: Python :: 3.7
Classifier: Programming Language :: Python :: 3.8
Classifier: Programming Language :: Python :: 3.9
Classifier: Programming Language :: Python :: 3.10
Classifier: Programming Language :: Python :: Implementation :: CPython
Classifier: Programming Language :: Python :: Implementation :: PyPy
Classifier: Topic :: Internet :: WWW/HTTP
Classifier: Topic :: Text Processing :: Markup :: HTML
Classifier: Topic :: Multimedia :: Graphics :: Graphics Conversion
Classifier: Topic :: Printing
Requires-Dist: pydyf >=0.0.3
Requires-Dist: cffi >=0.6
Requires-Dist: html5lib >=1.1
Requires-Dist: tinycss2 >=1.0.0
Requires-Dist: cssselect2 >=0.1
Requires-Dist: Pyphen >=0.9.1
Requires-Dist: Pillow >=4.0.0
Requires-Dist: fonttools[woff] >=4.0.0
Requires-Dist: sphinx ; extra == "doc"
Requires-Dist: sphinx_rtd_theme ; extra == "doc"
Requires-Dist: pytest ; extra == "test"
Requires-Dist: pytest-cov ; extra == "test"
Requires-Dist: pytest-flake8 ; extra == "test"
Requires-Dist: pytest-isort ; extra == "test"
Requires-Dist: coverage[toml] ; extra == "test"
Project-URL: Changelog, https://github.com/Kozea/WeasyPrint/releases
Project-URL: Code, https://github.com/Kozea/WeasyPrint
Project-URL: Documentation, https://doc.courtbouillon.org/weasyprint/
Project-URL: Donation, https://opencollective.com/courtbouillon
Project-URL: Homepage, https://www.courtbouillon.org/weasyprint
Project-URL: Issues, https://github.com/Kozea/WeasyPrint/issues
Provides-Extra: doc
Provides-Extra: test
